[
  {
    "venue_id": "9d94692f-b939-4ec3-847b-97bc7ccfd844",
    "venue_name": "Expansive - North First",
    "latitude": 37.37727,
    "longitude": -121.920334,
    "reservations": 282,
    "spend": 61776.0
  },
  {
    "venue_id": "85061ae0-cd8c-4364-a569-69bd69d0188e",
    "venue_name": "SPACES | Santana Row",
    "latitude": 37.317535,
    "longitude": -121.947624,
    "reservations": 17,
    "spend": 6046.65
  },
  {
    "venue_id": "a4d5fd04-bc63-4484-97eb-9cd3255c9e40",
    "venue_name": "Regus || Downtown San Jose",
    "latitude": 37.332584,
    "longitude": -121.89431,
    "reservations": 29,
    "spend": 4791.75
  },
  {
    "venue_id": "c79ce97f-3fab-40fe-a7fc-39a99a3ba066",
    "venue_name": "HQ | CA, San Jose - North San Jose",
    "latitude": 37.396137,
    "longitude": -121.928436,
    "reservations": 13,
    "spend": 2431.77
  },
  {
    "venue_id": "2d537039-65f9-4191-a24d-b915d3a2b363",
    "venue_name": "Silicon Valley Business Center",
    "latitude": 37.26165,
    "longitude": -121.923103,
    "reservations": 15,
    "spend": 1830.0
  },
  {
    "venue_id": "23abbae6-932d-499a-a20c-0c1e8235eb17",
    "venue_name": "Regus | CA, San Jose - South San Jose",
    "latitude": 37.236401,
    "longitude": -121.778,
    "reservations": 11,
    "spend": 506.26
  },
  {
    "venue_id": "a5e1d1d2-fb03-4cb5-8e16-0bff7c14fdc0",
    "venue_name": "(SJ2) Silicon Valley Center",
    "latitude": 37.3853,
    "longitude": -121.924828,
    "reservations": 1,
    "spend": 255.0
  },
  {
    "venue_id": "2a9efa7e-e69b-415b-a85c-8563c0bce30f",
    "venue_name": "Pacific Workplaces - San Jose",
    "latitude": 37.335274,
    "longitude": -121.891525,
    "reservations": 7,
    "spend": 210.0
  },
  {
    "venue_id": "e0fb972e-1999-42ca-8079-5320837d5499",
    "venue_name": "WeWork | Riverpark Tower",
    "latitude": 37.328873,
    "longitude": -121.89357,
    "reservations": 2,
    "spend": 84.0
  }
]